proxycrawl/__init__.py
proxycrawl/base_api.py
proxycrawl/crawling_api.py
proxycrawl/leads_api.py
proxycrawl/proxycrawl_api.py
proxycrawl/scraper_api.py
proxycrawl/screenshots_api.py
proxycrawl/storage_api.py
proxycrawl-3.2.1.dist-info/LICENSE
proxycrawl-3.2.1.dist-info/METADATA
proxycrawl-3.2.1.dist-info/WHEEL
proxycrawl-3.2.1.dist-info/top_level.txt
proxycrawl-3.2.1.dist-info/RECORD
