Metadata-Version: 2.1
Name: proxycrawl
Version: 3.2.1
Summary: A Python class that acts as wrapper for ProxyCrawl scraping and crawling API
Home-page: https://github.com/proxycrawl/proxycrawl-python
Author: ProxyCrawl
Author-email: info@proxycrawl.com
License: Apache-2.0
Keywords: scraping scraper crawler crawling proxycrawl api
Platform: UNKNOWN
Classifier: Programming Language :: Python :: 2
Classifier: Programming Language :: Python :: 2.7
Classifier: Programming Language :: Python :: 3
Classifier: Programming Language :: Python :: 3.5
Classifier: Programming Language :: Python :: 3.9
Classifier: Development Status :: 5 - Production/Stable
Classifier: Intended Audience :: Developers
Classifier: License :: OSI Approved :: Apache Software License
Classifier: Operating System :: OS Independent
Classifier: Topic :: Utilities
License-File: LICENSE
